refac/__init__.py
refac/__main__.py
refac/move_file.py
refac/move_import.py
refac/move_symbol.py
refac/py.typed
refac/replace_str.py
refac/utils.py
refac/visitors/__init__.py
refac/visitors/add_symbols.py
refac/visitors/import_utils.py
refac/visitors/inplace_replace_import.py
refac/visitors/remove_symbols.py
refac/visitors/replace_import.py
refac-0.0.5.dist-info/LICENSE
refac-0.0.5.dist-info/METADATA
refac-0.0.5.dist-info/WHEEL
refac-0.0.5.dist-info/entry_points.txt
refac-0.0.5.dist-info/top_level.txt
refac-0.0.5.dist-info/RECORD
