Metadata-Version: 2.1
Name: refac
Version: 0.0.5
Summary: Tool to move around Python source code.
Home-page: https://github.com/benchling/refac
Author: Benchling Open Source
Author-email: opensource@benchling.com
Maintainer: Benchling Open Source
Maintainer-email: opensource@benchling.com
License: MIT License
Keywords: refactor,symbol,move
Classifier: Intended Audience :: Developers
Classifier: Natural Language :: English
Classifier: Programming Language :: Python :: 3
Classifier: Topic :: Software Development :: Libraries :: Python Modules
License-File: LICENSE
Requires-Dist: libcst
